devpi_mirror_index_acl.py
devpi_mirror_index_acl-1.0.0.dist-info/LICENSE
devpi_mirror_index_acl-1.0.0.dist-info/METADATA
devpi_mirror_index_acl-1.0.0.dist-info/WHEEL
devpi_mirror_index_acl-1.0.0.dist-info/entry_points.txt
devpi_mirror_index_acl-1.0.0.dist-info/top_level.txt
devpi_mirror_index_acl-1.0.0.dist-info/RECORD
