Metadata-Version: 2.1
Name: devpi-mirror-index-acl
Version: 1.0.0
Summary: Add command line option to limit mirror index creation to specific users.
Maintainer-email: Florian Schulze <mail@pyfidelity.com>
License: MIT License
Requires-Python: >=3.8
License-File: LICENSE
Requires-Dist: devpi-server >=6.9.0
